exgep/__init__.py
exgep/model/__init__.py
exgep/model/classification.py
exgep/model/classifiers.py
exgep/model/model.py
exgep/model/regression.py
exgep/model/regressors.py
exgep/preprocess/__init__.py
exgep/preprocess/datautils.py
exgep/preprocess/readvcf.py
exgep/utils/__init__.py
exgep/utils/function_helper.py
exgep/utils/metrics.py
exgep/utils/misc.py
exgep/utils/scalers_transformers.py
tools/__init__.py
tools/test_exgep.py
tools/test_explain.py
EXGEP-0.1.3.dist-info/METADATA
EXGEP-0.1.3.dist-info/WHEEL
EXGEP-0.1.3.dist-info/top_level.txt
EXGEP-0.1.3.dist-info/RECORD
