Metadata-Version: 2.1
Name: EXGEP
Version: 0.1.3
Summary: A framework for predicting genotype-by-environment interactions using ensembles of explainable machine-learning models
Home-page: https://github.com/AIBreeding/EXGEP
Classifier: Programming Language :: Python :: 3.9
Classifier: License :: OSI Approved :: MIT License
Classifier: Operating System :: MacOS :: MacOS X
Classifier: Operating System :: Microsoft :: Windows
Classifier: Operating System :: POSIX :: Linux
Requires-Python: >=3.9
Requires-Dist: alembic (==1.13.2)
Requires-Dist: catboost (==1.2.5)
Requires-Dist: cloudpickle (==3.0.0)
Requires-Dist: colorama (==0.4.6)
Requires-Dist: colorlog (==6.8.2)
Requires-Dist: contourpy (==1.1.1)
Requires-Dist: cycler (==0.12.1)
Requires-Dist: fonttools (==4.53.1)
Requires-Dist: graphviz (==0.20.3)
Requires-Dist: greenlet (==3.0.3)
Requires-Dist: importlib-metadata (==8.2.0)
Requires-Dist: importlib-resources (==6.4.0)
Requires-Dist: joblib (==1.4.2)
Requires-Dist: kiwisolver (==1.4.5)
Requires-Dist: lightgbm (==4.5.0)
Requires-Dist: llvmlite (==0.41.1)
Requires-Dist: Mako (==1.3.5)
Requires-Dist: MarkupSafe (==2.1.5)
Requires-Dist: matplotlib (==3.7.5)
Requires-Dist: networkx (==3.1)
Requires-Dist: numba (==0.58.1)
Requires-Dist: numpy (==1.24.4)
Requires-Dist: optuna (==3.6.1)
Requires-Dist: packaging (==24.1)
Requires-Dist: pandas (==2.0.3)
Requires-Dist: pillow (==10.4.0)
Requires-Dist: plotly (==5.23.0)
Requires-Dist: pyparsing (==3.1.2)
Requires-Dist: python-dateutil (==2.9.0.post0)
Requires-Dist: pytz (==2024.1)
Requires-Dist: PyYAML (==6.0.2)
Requires-Dist: scikit-learn (==1.3.2)
Requires-Dist: scipy (==1.10.1)
Requires-Dist: shap (==0.44.1)
Requires-Dist: six (==1.16.0)
Requires-Dist: slicer (==0.0.7)
Requires-Dist: SQLAlchemy (==2.0.32)
Requires-Dist: tenacity (==9.0.0)
Requires-Dist: threadpoolctl (==3.5.0)
Requires-Dist: tqdm (==4.66.5)
Requires-Dist: typing-extensions (==4.12.2)
Requires-Dist: tzdata (==2024.1)
Requires-Dist: xgboost (==2.0.3)
Requires-Dist: zipp (==3.19.2)
